__init__.py
_internals.py
plugin.py
py.typed
pytest_pyspark_plugin-0.2.0.dist-info/METADATA
pytest_pyspark_plugin-0.2.0.dist-info/WHEEL
pytest_pyspark_plugin-0.2.0.dist-info/entry_points.txt
pytest_pyspark_plugin-0.2.0.dist-info/licenses/LICENSE.md
pytest_pyspark_plugin-0.2.0.dist-info/RECORD
