Metadata-Version: 2.4
Name: pytest-pyspark-plugin
Version: 0.2.0
Summary: Pytest pyspark plugin (p3)
Author: mk.fshr
License-File: LICENSE.md
Classifier: Development Status :: 4 - Beta
Classifier: Framework :: Pytest
Classifier: Intended Audience :: Developers
Classifier: Programming Language :: Python :: 3.11
Classifier: Programming Language :: Python :: 3.12
Classifier: Programming Language :: Python :: 3.13
Classifier: Topic :: Software Development :: Testing
Requires-Python: >=3.11
Requires-Dist: pyspark[connect]>=3.5.1
Requires-Dist: pytest>=8.0.0
Requires-Dist: setuptools>=75.8.0
